servie/__init__.py
servie/client.py
servie/server.py
servie-1.0.2.dev1.dist-info/METADATA
servie-1.0.2.dev1.dist-info/WHEEL
servie-1.0.2.dev1.dist-info/top_level.txt
servie-1.0.2.dev1.dist-info/RECORD
